greenideas/__init__.py
greenideas/__main__.py
greenideas/attributes/attribute_set.py
greenideas/attributes/attribute_type.py
greenideas/attributes/grammatical_attribute.py
greenideas/default_dictionary/.git
greenideas/default_dictionary/LICENSE
greenideas/default_dictionary/README.md
greenideas/default_dictionary/adj.dic
greenideas/default_dictionary/adv.dic
greenideas/default_dictionary/aux.dic
greenideas/default_dictionary/be.dic
greenideas/default_dictionary/conj.dic
greenideas/default_dictionary/deg.dic
greenideas/default_dictionary/det.dic
greenideas/default_dictionary/modal.dic
greenideas/default_dictionary/noun.dic
greenideas/default_dictionary/prep.dic
greenideas/default_dictionary/pron.dic
greenideas/default_dictionary/rel.dic
greenideas/default_dictionary/verb.dic
greenideas/exceptions.py
greenideas/grammar_engine.py
greenideas/parts_of_speech/pos_node.py
greenideas/parts_of_speech/pos_type_base.py
greenideas/rules/__init__.py
greenideas/rules/default_english_rules/__init__.py
greenideas/rules/default_english_rules/attributes/__init__.py
greenideas/rules/default_english_rules/attributes/animacy.py
greenideas/rules/default_english_rules/attributes/aspect.py
greenideas/rules/default_english_rules/attributes/case.py
greenideas/rules/default_english_rules/attributes/default_english_attribute_type.py
greenideas/rules/default_english_rules/attributes/mood.py
greenideas/rules/default_english_rules/attributes/npform.py
greenideas/rules/default_english_rules/attributes/number.py
greenideas/rules/default_english_rules/attributes/person.py
greenideas/rules/default_english_rules/attributes/tense.py
greenideas/rules/default_english_rules/attributes/valency.py
greenideas/rules/default_english_rules/attributes/voice.py
greenideas/rules/default_english_rules/default_rules.py
greenideas/rules/default_english_rules/expansions/__init__.py
greenideas/rules/default_english_rules/expansions/adjP_expansions.py
greenideas/rules/default_english_rules/expansions/advP_expansions.py
greenideas-0.10.0.dist-info/LICENSE
greenideas-0.10.0.dist-info/METADATA
greenideas-0.10.0.dist-info/WHEEL
greenideas-0.10.0.dist-info/RECORD
