Metadata-Version: 2.3
Name: greenideas
Version: 0.10.0
Summary: A package to generate grammatically valid but semantically nonsensical English sentences.
License: MIT
Keywords: grammar,procedural generation,sentence generation,placeholder text,twaddle
Author: Chris Hengler
Author-email: chrysics@gmail.com
Requires-Python: >=3.11
Classifier: License :: OSI Approved :: MIT License
Classifier: Programming Language :: Python :: 3
Classifier: Programming Language :: Python :: 3.11
Classifier: Programming Language :: Python :: 3.12
Classifier: Programming Language :: Python :: 3.13
Requires-Dist: pytest (>=7.2.0)
Requires-Dist: twaddle (>=1.2.2)
Project-URL: Repository, https://github.com/chrishengler/greenideas
